Metadata-Version: 2.1
Name: MTA-SDK-Python
Version: 0.1.0
Summary: A Python SDK To MTA
Author: Lucas Camargo de Andrade
Author-email: lucas.camargo.de.andrade15@gmail.com
License: MIT License
Keywords: MTA SDK Python
License-File: LICENSE
